rt_stoppers_contrib/__init__.py
rt_stoppers_contrib/no_improvement.py
rt_stoppers_contrib/threshold_by_epoch.py
rt_stoppers_contrib-1.1.2.dist-info/LICENSE.txt
rt_stoppers_contrib-1.1.2.dist-info/METADATA
rt_stoppers_contrib-1.1.2.dist-info/WHEEL
rt_stoppers_contrib-1.1.2.dist-info/top_level.txt
rt_stoppers_contrib-1.1.2.dist-info/RECORD
