Metadata-Version: 2.1
Name: rt-stoppers-contrib
Version: 1.1.2
Summary: Additional stoppers for ray tune
Home-page: https://github.com/klieret/ray-tune-stoppers-contrib
Author: Kilian Lieret
Author-email: kilian.lieret@posteo.de
Maintainer: Kilian Lieret
Maintainer-email: kilian.lieret@posteo.de
License: MIT
Project-URL: Bug Tracker, https://github.com/klieret/ray-tune-stoppers-contrib/issues
Project-URL: Documentation, https://rt_stoppers_contrib.readthedocs.io/
Project-URL: Source Code, https://github.com/klieret/ray-tune-stoppers-contrib
Classifier: License :: OSI Approved :: MIT License
Classifier: Operating System :: OS Independent
Classifier: Programming Language :: Python :: 3
Classifier: Programming Language :: Python :: 3 :: Only
Classifier: Programming Language :: Python :: 3.7
Classifier: Programming Language :: Python :: 3.8
Classifier: Programming Language :: Python :: 3.9
Classifier: Programming Language :: Python :: 3.10
Requires-Python: >=3.7
License-File: LICENSE.txt
Requires-Dist: ray[tune]
Provides-Extra: testing
Requires-Dist: pytest ; extra == 'testing'
Requires-Dist: pytest-coverage ; extra == 'testing'
